README.md
hi_tea.py
setup.py
limingggTEA.egg-info/PKG-INFO
limingggTEA.egg-info/SOURCES.txt
limingggTEA.egg-info/dependency_links.txt
limingggTEA.egg-info/entry_points.txt
limingggTEA.egg-info/requires.txt
limingggTEA.egg-info/top_level.txt